mathutils/__init__.py
mathutils/operations.py
omkars_add_sub_mathops_first-0.1.1.dist-info/METADATA
omkars_add_sub_mathops_first-0.1.1.dist-info/WHEEL
omkars_add_sub_mathops_first-0.1.1.dist-info/top_level.txt
omkars_add_sub_mathops_first-0.1.1.dist-info/RECORD
